sonusai_keras/__init__.py
sonusai_keras/data_generator/__init__.py
sonusai_keras/data_generator/dataset_from_mixdb.py
sonusai_keras/data_generator/keras_from_mixdb.py
sonusai_keras/keras_onnx.py
sonusai_keras/keras_predict.py
sonusai_keras/keras_train.py
sonusai_keras/utils/__init__.py
sonusai_keras/utils/keras_utils.py
sonusai_keras-0.1.0.dist-info/METADATA
sonusai_keras-0.1.0.dist-info/WHEEL
sonusai_keras-0.1.0.dist-info/RECORD
